{
  "generator-jhipster": {
    "applicationType": "monolith",
    "gitHubOrganization": "toztemel",
    "baseName": "jhipsterSampleApplication",
    "packageName": "io.github.toztemel.jhipster.application",
    "packageFolder": "io/github/toztemel/jhipster/application",
    "serverPort": 8080,
    "serviceDiscoveryType": false,
    "authenticationType": "jwt",
    "uaaBaseName": "../uaa",
    "cacheProvider": "no",
    "enableHibernateCache": false,
    "websocket": false,
    "databaseType": "mongodb",
    "devDatabaseType": "mongodb",
    "prodDatabaseType": "mongodb",
    "searchEngine": false,
    "enableSwaggerCodegen": false,
    "messageBroker": false,
    "buildTool": "gradle",
    "useSass": false,
    "clientPackageManager": "yarn",
    "testFrameworks": [],
    "enableTranslation": false,
    "nativeLanguage": "en",
    "languages": [
      "en"
    ],
    "clientFramework": "react"
  }
}